setup.py
Catnap.egg-info/PKG-INFO
Catnap.egg-info/SOURCES.txt
Catnap.egg-info/dependency_links.txt
Catnap.egg-info/requires.txt
Catnap.egg-info/top_level.txt
catnap/__init__.py
catnap/compat.py
catnap/models.py
catnap/tabbing.py
catnap/worker.py
catnap/yaml_parser.py
scripts/catnap
test/test_models.py