Metadata-Version: 1.0
Name: Catnap
Version: 0.4.0
Summary: A script for running integration tests against RESTful/HTTP-based interfaces
Home-page: http://github.com/dailymuse/catnap
Author: Yusuf Simonson
Author-email: UNKNOWN
License: UNKNOWN
Platform: UNKNOWN
